minicline/__init__.py
minicline/cli.py
minicline/core.py
minicline/completion/__init__.py
minicline/completion/run_completion.py
minicline/templates/system_prompt.txt
minicline/tools/__init__.py
minicline/tools/ask_followup_question.py
minicline/tools/attempt_completion.py
minicline/tools/execute_command.py
minicline/tools/is_within_directory.py
minicline/tools/list_files.py
minicline/tools/read_file.py
minicline/tools/read_image.py
minicline/tools/replace_in_file.py
minicline/tools/search_files.py
minicline/tools/test_timeout.py
minicline/tools/write_to_file.py
minicline/tools/test_scripts/long_running_process.py
minicline-0.1.15.dist-info/METADATA
minicline-0.1.15.dist-info/WHEEL
minicline-0.1.15.dist-info/entry_points.txt
minicline-0.1.15.dist-info/licenses/LICENSE
minicline-0.1.15.dist-info/RECORD
