Metadata-Version: 2.4
Name: minicline
Version: 0.1.15
Summary: Command-line interface for executing tasks using large language models, minimal version of Cline
Project-URL: Repository, https://github.com/magland/minicline
Author: Jeremy Magland
License: Apache-2.0
License-File: LICENSE
Requires-Python: >=3.8
Requires-Dist: click>=8.0.0
Requires-Dist: python-dotenv>=0.19.0
Requires-Dist: requests
